AUTHORS
LICENSE
MANIFEST.in
README.rst
setup.py
django_common/__init__.py
django_common/admin.py
django_common/auth_backends.py
django_common/classmaker.py
django_common/compat.py
django_common/context_processors.py
django_common/db_fields.py
django_common/decorators.py
django_common/email_backends.py
django_common/helper.py
django_common/http.py
django_common/middleware.py
django_common/mixin.py
django_common/scaffold.py
django_common/session.py
django_common/settings.py
django_common/tests.py
django_common/tzinfo.py
django_common/management/__init__.py
django_common/management/commands/__init__.py
django_common/management/commands/scaffold.py
django_common/static/django_common/js/ajax_form.js
django_common/static/django_common/js/common.js
django_common/templates/common/admin/nested.html
django_common/templates/common/admin/nested_tabular.html
django_common/templates/common/fragments/checkbox_field.html
django_common/templates/common/fragments/form_field.html
django_common/templates/common/fragments/multi_checkbox_field.html
django_common/templates/common/fragments/radio_field.html
django_common/templatetags/__init__.py
django_common/templatetags/custom_tags.py
django_common_helpers.egg-info/PKG-INFO
django_common_helpers.egg-info/SOURCES.txt
django_common_helpers.egg-info/dependency_links.txt
django_common_helpers.egg-info/not-zip-safe
django_common_helpers.egg-info/requires.txt
django_common_helpers.egg-info/top_level.txt