Metadata-Version: 1.1
Name: django-common-helpers
Version: 0.7.0
Summary: Common things every Django app needs!
Home-page: http://github.com/tivix/django-common
Author: Tivix
Author-email: dev@tivix.com
License: UNKNOWN
Keywords: django
Platform: UNKNOWN
Classifier: Framework :: Django
Classifier: Intended Audience :: Developers
Classifier: Intended Audience :: System Administrators
Classifier: Operating System :: OS Independent
Classifier: Topic :: Software Development
